fastqc_tool/__init__.py
fastqc_tool/__main__.py
fastqc_tool/fastqc.py
fastqc_tool/main.py
fastqc_tool-0.21.dist-info/DESCRIPTION.rst
fastqc_tool-0.21.dist-info/METADATA
fastqc_tool-0.21.dist-info/RECORD
fastqc_tool-0.21.dist-info/WHEEL
fastqc_tool-0.21.dist-info/metadata.json
fastqc_tool-0.21.dist-info/top_level.txt
